gnt/__init__.py
gnt/cli.py
gnt/score.py
gnt-0.3.2.dist-info/AUTHORS.rst
gnt-0.3.2.dist-info/LICENSE
gnt-0.3.2.dist-info/METADATA
gnt-0.3.2.dist-info/WHEEL
gnt-0.3.2.dist-info/entry_points.txt
gnt-0.3.2.dist-info/top_level.txt
gnt-0.3.2.dist-info/RECORD
