Metadata-Version: 2.1
Name: gnt
Version: 0.3.2
Summary: Python packcage for caidentifying Genetic iNTeractions from combinatorial screening data.
Home-page: https://github.com/gpp-rnd/gnt
Author: Peter C. DeWeirdt
Author-email: petedeweirdt@gmail.com
License: MIT license
Keywords: gnt
Platform: UNKNOWN
Classifier: Development Status :: 2 - Pre-Alpha
Classifier: Intended Audience :: Developers
Classifier: License :: OSI Approved :: MIT License
Classifier: Natural Language :: English
Classifier: Programming Language :: Python :: 3
Classifier: Programming Language :: Python :: 3.7
Classifier: Programming Language :: Python :: 3.8
Requires-Python: >=3.7
Requires-Dist: Click (>=7.0)
Requires-Dist: pandas (>=1.0)
Requires-Dist: numpy (>=1.19)
Requires-Dist: statsmodels (>=0.11)
